django_to_galaxy/__init__.py
django_to_galaxy/admin/__init__.py
django_to_galaxy/admin/galaxy_element.py
django_to_galaxy/admin/galaxy_instance.py
django_to_galaxy/admin/galaxy_output_file.py
django_to_galaxy/admin/galaxy_user.py
django_to_galaxy/admin/history.py
django_to_galaxy/admin/invocation.py
django_to_galaxy/admin/tag.py
django_to_galaxy/admin/utils.py
django_to_galaxy/admin/workflow.py
django_to_galaxy/api/__init__.py
django_to_galaxy/api/serializers/asymetricslugrelatedfield.py
django_to_galaxy/api/serializers/create_dataset_collection.py
django_to_galaxy/api/serializers/create_history.py
django_to_galaxy/api/serializers/galaxy_instance.py
django_to_galaxy/api/serializers/galaxy_output_file.py
django_to_galaxy/api/serializers/galaxy_user.py
django_to_galaxy/api/serializers/history.py
django_to_galaxy/api/serializers/invocation.py
django_to_galaxy/api/serializers/invoke_workflow.py
django_to_galaxy/api/serializers/upload_to_history.py
django_to_galaxy/api/serializers/workflow.py
django_to_galaxy/api/urls.py
django_to_galaxy/api/views/create_dataset_collection.py
django_to_galaxy/api/views/create_history.py
django_to_galaxy/api/views/galaxy_instance.py
django_to_galaxy/api/views/galaxy_output_file.py
django_to_galaxy/api/views/galaxy_user.py
django_to_galaxy/api/views/history.py
django_to_galaxy/api/views/invocation.py
django_to_galaxy/api/views/invoke_workflow.py
django_to_galaxy/api/views/upload_to_history.py
django_to_galaxy/api/views/workflow.py
django_to_galaxy/apps.py
django_to_galaxy/migrations/0001_new_initial.py
django_to_galaxy/migrations/0002_rename_state_history_galaxy_state_and_more.py
django_to_galaxy/migrations/0003_invocation_create_time.py
django_to_galaxy/migrations/0004_alter_galaxyuser_email_galaxyoutputfile.py
django_to_galaxy/migrations/0005_alter_galaxyoutputfile_invocation_and_more.py
django_to_galaxy/migrations/0006_tag_history_tags_workflow_tags.py
django_to_galaxy-0.7.0.5.dist-info/METADATA
django_to_galaxy-0.7.0.5.dist-info/WHEEL
django_to_galaxy-0.7.0.5.dist-info/licenses/LICENSE
django_to_galaxy-0.7.0.5.dist-info/RECORD
